gubbe/__init__.py
gubbe/gubbe.py
gubbe/version.py
gubbe-0.0.0.dev0.dist-info/LICENSE
gubbe-0.0.0.dev0.dist-info/METADATA
gubbe-0.0.0.dev0.dist-info/WHEEL
gubbe-0.0.0.dev0.dist-info/entry_points.txt
gubbe-0.0.0.dev0.dist-info/top_level.txt
gubbe-0.0.0.dev0.dist-info/RECORD
