Metadata-Version: 2.1
Name: gubbe
Version: 0.0.0.dev0
Summary: Manage Minecraft Plugins with ease!
Home-page: https://github.com/VilhelmPrytz/gubbe
Author: Vilhelm Prytz
Author-email: vlhelm@prytznet.se
License: MIT
Platform: UNKNOWN
Classifier: Programming Language :: Python
Classifier: Programming Language :: Python :: 3.6
Classifier: Programming Language :: Python :: 3.7
Classifier: Programming Language :: Python :: 3.8
Classifier: Programming Language :: Python :: 3 :: Only
Classifier: Environment :: Console
Classifier: License :: OSI Approved :: MIT License
Classifier: Operating System :: MacOS :: MacOS X
Classifier: Operating System :: POSIX :: Linux
Classifier: Operating System :: Unix
Classifier: Natural Language :: English
Requires-Python: >=3.6
Requires-Dist: click
